pureport_client/__init__.py
pureport_client/__main__.py
pureport_client/client.py
pureport_client/exceptions.py
pureport_client/helpers.py
pureport_client/session.py
pureport_client/util.py
pureport_client/commands/__init__.py
pureport_client/commands/accounts/__init__.py
pureport_client/commands/accounts/api_keys.py
pureport_client/commands/accounts/audit_log.py
pureport_client/commands/accounts/billing.py
pureport_client/commands/accounts/connections.py
pureport_client/commands/accounts/consent.py
pureport_client/commands/accounts/invites.py
pureport_client/commands/accounts/invoices.py
pureport_client/commands/accounts/members.py
pureport_client/commands/accounts/metrics.py
pureport_client/commands/accounts/networks.py
pureport_client/commands/accounts/permissions.py
pureport_client/commands/accounts/ports.py
pureport_client/commands/accounts/roles.py
pureport_client/commands/accounts/supported_connections.py
pureport_client/commands/accounts/supported_ports.py
pureport_client/commands/cloud_regions/__init__.py
pureport_client/commands/cloud_services/__init__.py
pureport_client/commands/connections/__init__.py
pureport_client/commands/facilities/__init__.py
pureport_client/commands/gateways/__init__.py
pureport_client/commands/locations/__init__.py
pureport_client/commands/networks/__init__.py
pureport_client/commands/networks/connections.py
pureport_client/commands/options/__init__.py
pureport_client/commands/ports/__init__.py
pureport_client/commands/supported_connections/__init__.py
pureport_client/commands/tasks/__init__.py
test/__init__.py
test/unit/__init__.py
test/unit/test_exceptions.py
test/unit/test_init.py
test/unit/commands/__init__.py
test/unit/commands/_test_accounts_invoices.py
test/unit/commands/test_accounts.py
test/unit/commands/test_accounts_api_keys.py
test/unit/commands/test_accounts_audit_log.py
test/unit/commands/test_accounts_billing.py
test/unit/commands/test_accounts_connections.py
test/unit/commands/test_accounts_consent.py
pureport_client-1.0.12.dist-info/LICENSE.txt
pureport_client-1.0.12.dist-info/METADATA
pureport_client-1.0.12.dist-info/WHEEL
pureport_client-1.0.12.dist-info/entry_points.txt
pureport_client-1.0.12.dist-info/top_level.txt
pureport_client-1.0.12.dist-info/RECORD
